depthgen/SDR_compute.py
depthgen/__init__.py
depthgen/demo.py
depthgen/pytorch_DIW_scratch.py
depthgen/rmse_error_main.py
depthgen/data/__init__.py
depthgen/data/aligned_data_loader.py
depthgen/data/base_data_loader.py
depthgen/data/data_loader.py
depthgen/data/image_folder.py
depthgen/models/HG_model.py
depthgen/models/__init__.py
depthgen/models/base_model.py
depthgen/models/models.py
depthgen/options/__init__.py
depthgen/options/base_options.py
depthgen/options/test_options.py
depthgen/options/train_options.py
depthgen/util/__init__.py
depthgen/util/html.py
depthgen/util/image_pool.py
depthgen/util/png.py
depthgen/util/util.py
depthgen/util/visualizer.py
depthgen-0.2.dist-info/LICENSE
depthgen-0.2.dist-info/METADATA
depthgen-0.2.dist-info/WHEEL
depthgen-0.2.dist-info/top_level.txt
depthgen-0.2.dist-info/RECORD
