Metadata-Version: 2.1
Name: depthgen
Version: 0.2
Summary: generating depth map from single image
Home-page: http://github.com/jaroslaw-weber/depthgen
Author: Jaroslaw Weber
Author-email: jaroslawweber@gmail.com
License: MIT
Platform: UNKNOWN
